{
  "number": 61,
  "title": "Qualifications for Elected Membership",
  "chapterNumber": 4,
  "chapterTitle": "The Legislature",
  "content": [
    {
      "paragraph": 1,
      "text": "A person shall be qualified to be elected as a member of the Legislative Assembly if, and shall not be so qualified unless, he or she is a Caymanian, has attained the age of twenty-one years, is domiciled and resident in the Cayman Islands, and is otherwise qualified as a citizen."
    }
  ],
  "amendmentHistory": null,
  "crossReferences": [],
  "notes": "Eligibility requirements for elected members."
}
