{
  "number": 117,
  "title": "Commission for Standards in Public Life",
  "chapterNumber": 8,
  "chapterTitle": "Institutions Supporting Democracy",
  "content": [
    {
      "paragraph": 1,
      "text": "There shall be a Commission for Standards in Public Life which shall consist of a Chairman and between two and four other members appointed by the Governor after consultation with the Premier and the Leader of the Opposition."
    },
    {
      "paragraph": 2,
      "text": "The functions of the Commission shall include setting standards of integrity and ethical conduct for public officials, monitoring and investigating compliance, supervising registers of interests, and reporting to the Legislative Assembly."
    }
  ],
  "amendmentHistory": null,
  "crossReferences": [
    {
      "articleNumber": 44,
      "chapterNumber": 3,
      "description": "The Cabinet"
    },
    {
      "articleNumber": 116,
      "chapterNumber": 8,
      "description": "Human Rights Commission"
    }
  ],
  "notes": "Commission for Standards in Public Life."
}
